geesedb/__init__.py
geesedb/cmd/__init__.py
geesedb/cmd/gql.py
geesedb/cmd/sql.py
geesedb/connection/__init__.py
geesedb/connection/connection.py
geesedb/index/__init__.py
geesedb/index/authors_from_csv.py
geesedb/index/entities_from_csv.py
geesedb/index/fulltext_from_ciff.py
geesedb/index/fulltext_from_csv.py
geesedb/index/utils.py
geesedb/interpreter/__init__.py
geesedb/interpreter/metadata.py
geesedb/interpreter/translate.py
geesedb/resources/__init__.py
geesedb/resources/topics.py
geesedb/resources/topics-and-qrels/__init__.py
geesedb/resources/topics-and-qrels/qrels.backgroundlinking18.txt
geesedb/resources/topics-and-qrels/qrels.backgroundlinking19.txt
geesedb/resources/topics-and-qrels/qrels.core17.txt
geesedb/resources/topics-and-qrels/qrels.core18.txt
geesedb/resources/topics-and-qrels/qrels.robust04.txt
geesedb/resources/topics-and-qrels/topics.backgroundlinking18.processed.txt
geesedb/resources/topics-and-qrels/topics.backgroundlinking19.processed.txt
geesedb/resources/topics-and-qrels/topics.core17.processed.txt
geesedb/resources/topics-and-qrels/topics.core18.processed.txt
geesedb/resources/topics-and-qrels/topics.robust04.processed.txt
geesedb/search/__init__.py
geesedb/search/searcher.py
geesedb/search/retrieval_models/__init__.py
geesedb/search/retrieval_models/generic_text_retrieval_model.py
geesedb/search/retrieval_models/bag_of_words/__init__.py
geesedb/search/retrieval_models/bag_of_words/aggregate.py
geesedb/search/retrieval_models/bag_of_words/bow_retrieval_model.py
geesedb/search/retrieval_models/bag_of_words/conjunctive/__init__.py
geesedb/search/retrieval_models/bag_of_words/disjunctive/__init__.py
geesedb/search/retrieval_models/bag_of_words/disjunctive/disjunctive_retieval_model.py
geesedb/search/retrieval_models/bag_of_words/disjunctive/robertson_bm25.py
geesedb/search/retrieval_models/graph/__init__.py
geesedb/search/retrieval_models/positional/__init__.py
geesedb/tests/__init__.py
geesedb/tests/connection/__init__.py
geesedb-0.0.2.dist-info/LICENSE
geesedb-0.0.2.dist-info/METADATA
geesedb-0.0.2.dist-info/WHEEL
geesedb-0.0.2.dist-info/top_level.txt
geesedb-0.0.2.dist-info/RECORD
